{
    "cli": {
        "version": ">= 16.28.0",
        "appVersionSource": "remote"
    },
    "build": {
        "development": {
            "developmentClient": true,
            "distribution": "internal"
        },
        "preview": {
            "distribution": "internal",
            "android": {
                "buildType": "apk"
            },
            "env": {
                "EXPO_PUBLIC_SUPABASE_URL": "https://vegkccmiluqfozynqnuf.supabase.co",
                "EXPO_PUBLIC_SUPABASE_ANON_KEY": "eyJhbGciOiJIUzI1NiIsInR5cCI6IkpXVCJ9.eyJpc3MiOiJzdXBhYmFzZSIsInJlZiI6InZlZ2tjY21pbHVxZm96eW5xbnVmIiwicm9sZSI6ImFub24iLCJpYXQiOjE3Njk0OTk0NjksImV4cCI6MjA4NTA3NTQ2OX0.077rLCfG0juWqnOVj5bBK7l5yQtzXheY-QDtJ0l_oPM"
            }
        },
        "production": {
            "android": {
                "buildType": "app-bundle"
            }
        }
    },
    "submit": {
        "production": {}
    }
}